<package>
  <description brief="Orogen-component for feature-detection in sonar_images">
  
  </description>
  <author>Fabio Zachert/fzachert@tzi.de</author>
  <license></license>
  <url>http://</url>
  <logo>http://</logo>
  <depend package="base/cmake" />
  <!--
   To add any dependencies use the depend tag
  <depend package="dummy-dependency-0" />
	...
  <depend package="dummy-dependency-n-1" />
  <depend package="dummy-dependency-n" />
  -->
  <depend package="base/types" />
  <depend package="cuslam/sonar_image_feature_extractor" />
</package>
